dockerfile_analyzer-0.3.7.dist-info/METADATA
dockerfile_analyzer-0.3.7.dist-info/WHEEL
dockerfile_analyzer-0.3.7.dist-info/licenses/LICENSE
dockerfile_analyzer/__init__.py
dockerfile_analyzer/__init__.pyi
dockerfile_analyzer/dockerfile_analyzer.cpython-314-i386-linux-gnu.so
dockerfile_analyzer/py.typed
dockerfile_analyzer-0.3.7.dist-info/RECORD
