Metadata-Version: 2.4
Name: dockerfile-analyzer
Version: 0.3.7
Classifier: Programming Language :: Rust
Classifier: Programming Language :: Python :: Implementation :: CPython
Classifier: Programming Language :: Python :: Implementation :: PyPy
License-File: LICENSE
Summary: Analyzes Dockerfiles and provides comprehensive insights including stage information, base images, multistage build analysis, instruction statistics, environment variables, labels, arguments, and exposed ports.
License-Expression: MIT
Requires-Python: >=3.13
Project-URL: Homepage, https://github.com/societymartingale/dockerfile-analyzer
Project-URL: Issues, https://github.com/societymartingale/dockerfile-analyzer/issues
